tubemixer/__init__.py
tubemixer/__main__.py
tubemixer/extractor.py
tubemixer-0.1.dist-info/METADATA
tubemixer-0.1.dist-info/WHEEL
tubemixer-0.1.dist-info/entry_points.txt
tubemixer-0.1.dist-info/top_level.txt
tubemixer-0.1.dist-info/RECORD
